markovbot/__init__.py
markovbot-0.1.data/scripts/markovbot
markovbot-0.1.dist-info/DESCRIPTION.rst
markovbot-0.1.dist-info/METADATA
markovbot-0.1.dist-info/RECORD
markovbot-0.1.dist-info/WHEEL
markovbot-0.1.dist-info/metadata.json
markovbot-0.1.dist-info/top_level.txt
