Metadata-Version: 2.0
Name: markovbot
Version: 0.1
Summary: Make a markov chain based twitter bot
Home-page: http://github.com/vmchale/markov-bot
Author: Vanessa McHale
Author-email: tmchale@wisc.edu
License: BSD3
Platform: UNKNOWN
Requires-Dist: markovify
Requires-Dist: python-twitter
